<?xml version="1.0" encoding="utf-8"?>
<VisualState xmlns:xsi="http://www.w3.org/2001/XMLSchema-instance" xmlns:xsd="http://www.w3.org/2001/XMLSchema" ShowCheckBoxes="false">
  <TopNode>[0-1000]C:\fabien\programmation\csharp\tutorials\RhinoMocks\Nunit.nunit</TopNode>
  <SelectedNode>[0-1000]C:\fabien\programmation\csharp\tutorials\RhinoMocks\Nunit.nunit</SelectedNode>
  <ExcludeCategories>false</ExcludeCategories>
  <Nodes>
    <Node UniqueName="[0-1000]C:\fabien\programmation\csharp\tutorials\RhinoMocks\Nunit.nunit" Expanded="true" />
    <Node UniqueName="[0-1008]C:\fabien\programmation\csharp\tutorials\RhinoMocks\00-RhinoMocksIntroduction\00-RhinoMocksIntroduction\bin\Release\RhinoMocksIntroduction.dll" Expanded="true" />
    <Node UniqueName="[0-1009]RhinoMocksIntroduction" Expanded="true" />
    <Node UniqueName="[0-1001]RhinoMocksIntroduction.RhinoMocksIntroductionTest" Expanded="true" />
    <Node UniqueName="[0-1013]C:\fabien\programmation\csharp\tutorials\RhinoMocks\01-RhinoMocksGenerics\01-RhinoMocksGenerics\bin\Release\RhinoMocksGenerics.dll" Expanded="true" />
    <Node UniqueName="[0-1014]RhinoMocksGenerics" Expanded="true" />
    <Node UniqueName="[0-1010]RhinoMocksGenerics.RhinoMocksGenericsTest" Expanded="true" />
    <Node UniqueName="[0-1018]C:\fabien\programmation\csharp\tutorials\RhinoMocks\02-RhinoMocksPartialMocks\02-RhinoMocksPartialMocks\bin\Release\RhinoMocksPartialMocks.dll" Expanded="true" />
    <Node UniqueName="[0-1019]RhinoMocksPartialMocks" Expanded="true" />
    <Node UniqueName="[0-1015]RhinoMocksPartialMocks.RhinoMocksPartialMocksTest" Expanded="true" />
    <Node UniqueName="[0-1025]C:\fabien\programmation\csharp\tutorials\RhinoMocks\03-RhinoMocksStubs\03-RhinoMocksStubs\bin\Release\RhinoMocksStubs.dll" Expanded="true" />
    <Node UniqueName="[0-1026]RhinoMocksStubs" Expanded="true" />
    <Node UniqueName="[0-1020]RhinoMocksStubs.RhinoMocksStubsTest" Expanded="true" />
    <Node UniqueName="[0-1032]C:\fabien\programmation\csharp\tutorials\RhinoMocks\04-RhinoMocksOrderedUnordered\04-RhinoMocksOrderedUnordered\bin\Release\RhinoMocksOrderedUnordered.dll" Expanded="true" />
    <Node UniqueName="[0-1033]RhinoMocksIntroduction" Expanded="true" />
    <Node UniqueName="[0-1027]RhinoMocksIntroduction.RhinoMocksOrderedUnorderedTest" Expanded="true" />
    <Node UniqueName="[0-1037]C:\fabien\programmation\csharp\tutorials\RhinoMocks\05-RhinoMocksMockingDelegates\05-RhinoMocksMockingDelegates\bin\Release\RhinoMockDelegates.dll" Expanded="true" />
    <Node UniqueName="[0-1038]RhinoMockDelegates" Expanded="true" />
    <Node UniqueName="[0-1034]RhinoMockDelegates.RhinoMocksMockingDelegatesTest" Expanded="true" />
    <Node UniqueName="[0-1044]C:\fabien\programmation\csharp\tutorials\RhinoMocks\06-RhinoMocksEvents\06-RhinoMocksEvents\bin\Release\RhinoMocksEvents.dll" Expanded="true" />
    <Node UniqueName="[0-1045]RhinoMocksEvents" Expanded="true" />
    <Node UniqueName="[0-1049]C:\fabien\programmation\csharp\tutorials\RhinoMocks\07-RhinoMocksIEventRaiser\07-RhinoMocksIEventRaiser\bin\Release\RhinoMocksIEventRaiser.dll" Expanded="true" />
    <Node UniqueName="[0-1050]RhinoMocksIEventRaiser" Expanded="true" />
    <Node UniqueName="[0-1058]C:\fabien\programmation\csharp\tutorials\RhinoMocks\08-RhinoMocksProperties\08-RhinoMocksProperties\bin\Release\RhinoMocksProperties.dll" Expanded="true" />
    <Node UniqueName="[0-1059]RhinoMocksProperties" Expanded="true" />
    <Node UniqueName="[0-1051]RhinoMocksProperties.RhinoMocksPropertiesTest" Expanded="true" />
    <Node UniqueName="[0-1063]C:\fabien\programmation\csharp\tutorials\RhinoMocks\09-RhinoMocksTheDoHandler\09-RhinoMocksTheDoHandler\bin\Release\RhinoMocksTheDoHandler.dll" Expanded="true" />
    <Node UniqueName="[0-1064]RhinoMocksTheDoHandler" Expanded="true" />
    <Node UniqueName="[0-1060]RhinoMocksTheDoHandler.RhinoMocksTheDoHandlerTest" Expanded="true" />
    <Node UniqueName="[0-1068]C:\fabien\programmation\csharp\tutorials\RhinoMocks\10-RhinoMocksConstraints\10-RhinoMocksConstraints\bin\Release\RhinoMocksConstraints.dll" Expanded="true" />
    <Node UniqueName="[0-1069]RhinoMocksConstraints" Expanded="true" />
    <Node UniqueName="[0-1065]RhinoMocksConstraints.RhinoMocksConstraintsTest" Expanded="true" />
    <Node UniqueName="[0-1087]C:\fabien\programmation\csharp\tutorials\RhinoMocks\11-RhinoMocksMethodOptions\11-RhinoMocksMethodOptions\bin\Release\RhinoMocksMethodOptions.dll" Expanded="true" />
    <Node UniqueName="[0-1088]RhinoMocksMethodOptions" Expanded="true" />
    <Node UniqueName="[0-1070]RhinoMocksMethodOptions.RhinoMocksMethodOptionsTest" Expanded="true" />
    <Node UniqueName="[0-1091]C:\fabien\programmation\csharp\tutorials\RhinoMocks\12-RhinoMocksSetupResult\12-RhinoMocksSetupResult\bin\Release\RhinoMocksSetupResult.dll" Expanded="true" />
    <Node UniqueName="[0-1092]RhinoMocksSetupResult" Expanded="true" />
    <Node UniqueName="[0-1089]RhinoMocksSetupResult.RhinoMocksSetupResultTest" Expanded="true" />
    <Node UniqueName="[0-1097]C:\fabien\programmation\csharp\tutorials\RhinoMocks\13-RhinoMocksMockingClasses\13-RhinoMocksMockingClasses\bin\Release\RhinoMocksMockingClasses.dll" Expanded="true" />
    <Node UniqueName="[0-1098]RhinoMocksMockingClasses" Expanded="true" />
    <Node UniqueName="[0-1101]C:\fabien\programmation\csharp\tutorials\RhinoMocks\14-RhinoMocksInternalMembers\14-RhinoMocksInternalMembers\bin\Release\RhinoMocksInternalMembers.dll" Expanded="true" />
    <Node UniqueName="[0-1102]RhinoMocksInternalMembers" Expanded="true" />
    <Node UniqueName="[0-1105]C:\fabien\programmation\csharp\tutorials\RhinoMocks\15-RhinoMocksRecordPlaybackSyntax\15-RhinoMocksRecordPlaybackSyntax\bin\Release\RhinoMocksRecordPlaybackSyntax.dll" Expanded="true" />
    <Node UniqueName="[0-1106]RhinoMocksRecordPlaybackSyntax" Expanded="true" />
    <Node UniqueName="[0-1110]C:\fabien\programmation\csharp\tutorials\RhinoMocks\16-RhinoMocksWithSyntax\16-RhinoMocksWithSyntax\bin\Release\RhinoMocksWithSyntax.dll" Expanded="true" />
    <Node UniqueName="[0-1111]RhinoMocksWithSyntax" Expanded="true" />
  </Nodes>
</VisualState>